policy/__init__.py
policy/_cache.py
policy/_parser.py
policy/_utils.py
policy/checks.py
policy/enforcer.py
policy/exceptions.py
policy/tests/__init__.py
policy-1.0.0.dist-info/METADATA
policy-1.0.0.dist-info/RECORD
policy-1.0.0.dist-info/WHEEL
policy-1.0.0.dist-info/top_level.txt
